visorRobot/__init__.py
visorRobot/visor.py
visorRobot01-0.0.1.dist-info/METADATA
visorRobot01-0.0.1.dist-info/WHEEL
visorRobot01-0.0.1.dist-info/top_level.txt
visorRobot01-0.0.1.dist-info/RECORD
